inapppy/__init__.py
inapppy/appstore.py
inapppy/errors.py
inapppy/googleplay.py
inapppy/asyncio/__init__.py
inapppy/asyncio/appstore.py
inapppy2-2.4.5.dist-info/LICENSE
inapppy2-2.4.5.dist-info/METADATA
inapppy2-2.4.5.dist-info/WHEEL
inapppy2-2.4.5.dist-info/top_level.txt
inapppy2-2.4.5.dist-info/RECORD
