Metadata-Version: 2.1
Name: inapppy2
Version: 2.4.5
Summary: In-app purchase validation library for Apple AppStore and GooglePlay.
Home-page: https://github.com/Nkhinatolla/InAppPy.git
Author: Lukas Šalkauskas
Author-email: halfas.online@gmail.com
License: MIT
Keywords: in-app store purchase googleplay appstore validation
Platform: UNKNOWN
Classifier: Programming Language :: Python :: 3
Classifier: License :: OSI Approved :: MIT License
Classifier: Operating System :: OS Independent
Requires-Dist: aiohttp
Requires-Dist: rsa
Requires-Dist: requests
Requires-Dist: google-api-python-client
